pypyrus_tables/__init__.py
pypyrus_tables/parser.py
pypyrus_tables/table.py
pypyrus_tables-0.0.2.dist-info/LICENCE
pypyrus_tables-0.0.2.dist-info/METADATA
pypyrus_tables-0.0.2.dist-info/WHEEL
pypyrus_tables-0.0.2.dist-info/top_level.txt
pypyrus_tables-0.0.2.dist-info/RECORD
